atk_training_dinesh_wf_basic/__init__.py
atk_training_dinesh_wf_basic-0.2.0.dist-info/METADATA
atk_training_dinesh_wf_basic-0.2.0.dist-info/WHEEL
atk_training_dinesh_wf_basic-0.2.0.dist-info/entry_points.txt
atk_training_dinesh_wf_basic-0.2.0.dist-info/RECORD
