Metadata-Version: 2.1
Name: atk-training-dinesh-wf-basic
Version: 0.2.0
Summary: 
Author: dinesh-acog
Author-email: dinesh@aganitha.ai
Requires-Python: >=3.11,<4.0
Classifier: Programming Language :: Python :: 3
Classifier: Programming Language :: Python :: 3.11
Classifier: Programming Language :: Python :: 3.12
Requires-Dist: requests (>=2.31.0,<3.0.0)
Requires-Dist: typer (>=0.9.0,<0.10.0)
